agent_assist/__init__.py
agent_assist/agent_assist.py
dfcx_scrapi/__init__.py
dfcx_scrapi/agent_extract/__init__.py
dfcx_scrapi/agent_extract/agents.py
dfcx_scrapi/agent_extract/common.py
dfcx_scrapi/agent_extract/entity_types.py
dfcx_scrapi/agent_extract/flows.py
dfcx_scrapi/agent_extract/gcs_utils.py
dfcx_scrapi/agent_extract/graph.py
dfcx_scrapi/agent_extract/intents.py
dfcx_scrapi/agent_extract/pages.py
dfcx_scrapi/agent_extract/route_groups.py
dfcx_scrapi/agent_extract/routes.py
dfcx_scrapi/agent_extract/test_cases.py
dfcx_scrapi/agent_extract/types.py
dfcx_scrapi/agent_extract/webhooks.py
dfcx_scrapi/builders/__init__.py
dfcx_scrapi/builders/agents.py
dfcx_scrapi/builders/builders_common.py
dfcx_scrapi/builders/entity_types.py
dfcx_scrapi/builders/flows.py
dfcx_scrapi/builders/fulfillments.py
dfcx_scrapi/builders/generative_settings.py
dfcx_scrapi/builders/intents.py
dfcx_scrapi/builders/pages.py
dfcx_scrapi/builders/response_messages.py
dfcx_scrapi/builders/routes.py
dfcx_scrapi/builders/transition_route_groups.py
dfcx_scrapi/core/__init__.py
dfcx_scrapi/core/agents.py
dfcx_scrapi/core/changelogs.py
dfcx_scrapi/core/conversation.py
dfcx_scrapi/core/conversation_history.py
dfcx_scrapi/core/data_stores.py
dfcx_scrapi/core/engines.py
dfcx_scrapi/core/entity_types.py
dfcx_scrapi/core/environments.py
dfcx_scrapi/core/examples.py
dfcx_scrapi/core/experiments.py
dfcx_scrapi/core/flows.py
dfcx_scrapi/core/generators.py
dfcx_scrapi/core/intents.py
dfcx_scrapi/core/operations.py
dfcx_scrapi/core/pages.py
dfcx_scrapi/core/playbooks.py
dfcx_scrapi/core/project.py
dfcx_scrapi/core/scrapi_base.py
dfcx_scrapi/core/search.py
dfcx_scrapi/core/security_settings.py
dfcx_scrapi/core/session_entity_types.py
dfcx_scrapi/core/sessions.py
dfcx_scrapi/core/sites.py
dfcx_scrapi/core/test_cases.py
dfcx_scrapi/core/tools.py
dfcx_scrapi/core/transition_route_groups.py
dfcx_scrapi/core/versions.py
dfcx_scrapi/core/webhooks.py
dfcx_scrapi/core_async/__init__.py
dfcx_scrapi-1.13.0.dist-info/LICENSE.txt
dfcx_scrapi-1.13.0.dist-info/METADATA
dfcx_scrapi-1.13.0.dist-info/WHEEL
dfcx_scrapi-1.13.0.dist-info/top_level.txt
dfcx_scrapi-1.13.0.dist-info/RECORD
