Metadata-Version: 2.1
Name: dfcx-scrapi
Version: 1.13.0
Summary: A high level scripting API for bot builders, developers, and      maintainers.
Home-page: https://github.com/GoogleCloudPlatform/dfcx-scrapi
Author: Patrick Marlow
Author-email: pmarlow@google.com
Keywords: dialogflow,cx,google,bot,chatbot,intent,dfcx,entity
Classifier: Development Status :: 4 - Beta
Classifier: Intended Audience :: Developers
Classifier: Topic :: Scientific/Engineering :: Artificial Intelligence
Classifier: Topic :: Communications :: Chat
Classifier: Topic :: Software Development
Classifier: Programming Language :: Python :: 3
Classifier: Programming Language :: Python :: 3.8
Classifier: Programming Language :: Python :: 3.9
Requires-Python: >=3.6, <4
License-File: LICENSE.txt
Requires-Dist: google-cloud-dialogflow-cx
Requires-Dist: google-cloud-aiplatform
Requires-Dist: google-cloud-discoveryengine
Requires-Dist: rouge-score
